redbrick_slicer/__init__.py
redbrick_slicer/project.py
redbrick_slicer/slicer.py
redbrick_slicer/common/__init__.py
redbrick_slicer/common/client.py
redbrick_slicer/common/context.py
redbrick_slicer/common/export.py
redbrick_slicer/common/labeling.py
redbrick_slicer/common/project.py
redbrick_slicer/export/__init__.py
redbrick_slicer/export/public.py
redbrick_slicer/labeling/__init__.py
redbrick_slicer/labeling/public.py
redbrick_slicer/repo/__init__.py
redbrick_slicer/repo/export.py
redbrick_slicer/repo/labeling.py
redbrick_slicer/repo/project.py
redbrick_slicer/utils/__init__.py
redbrick_slicer/utils/async_utils.py
redbrick_slicer/utils/files.py
redbrick_slicer/utils/url.py
redbrick_slicer-0.1.3.dist-info/METADATA
redbrick_slicer-0.1.3.dist-info/WHEEL
redbrick_slicer-0.1.3.dist-info/top_level.txt
redbrick_slicer-0.1.3.dist-info/RECORD
