Metadata-Version: 2.1
Name: redbrick-slicer
Version: 0.1.3
Summary: RedBrick platform 3D Slicer Integration!
Home-page: https://github.com/redbrick-ai/redbrick-slicer
Requires-Python: >=3.6
Requires-Dist: requests (==2.23.0)
Requires-Dist: nibabel (==3.2.1)
Requires-Dist: tenacity (==8.0.1)
Requires-Dist: httpx (==0.22.0)
Provides-Extra: dev
Requires-Dist: twine (==3.1.1) ; extra == 'dev'
Requires-Dist: wheel (==0.35.1) ; extra == 'dev'
Requires-Dist: pytest-mock (==3.3.1) ; extra == 'dev'
Requires-Dist: pytest (==6.1.2) ; extra == 'dev'
Requires-Dist: black (==21.7b0) ; extra == 'dev'
Requires-Dist: mypy (==0.790) ; extra == 'dev'
Requires-Dist: mypy-extensions (==0.4.3) ; extra == 'dev'
Requires-Dist: pylint (==2.11.1) ; extra == 'dev'
Requires-Dist: pycodestyle (==2.6.0) ; extra == 'dev'
Requires-Dist: pydocstyle (==5.1.1) ; extra == 'dev'
Requires-Dist: flake8 (==3.8.4) ; extra == 'dev'
Requires-Dist: flake8-print (==3.1.4) ; extra == 'dev'
Requires-Dist: eradicate (==1.0) ; extra == 'dev'
Requires-Dist: pytest-cov (>=2.8.1) ; extra == 'dev'
Requires-Dist: pytest-asyncio (==0.12.0) ; extra == 'dev'
Requires-Dist: pytest-eradicate (==0.0.5) ; extra == 'dev'
Requires-Dist: pytest-pycodestyle (==2.2.0) ; extra == 'dev'
Requires-Dist: pytest-pydocstyle (==2.2.0) ; extra == 'dev'
Requires-Dist: pytest-black (==0.3.12) ; extra == 'dev'
Requires-Dist: pytest-pylint (==0.17.0) ; extra == 'dev'
Requires-Dist: pytest-mypy (==0.7.0) ; extra == 'dev'
Requires-Dist: pytest-flake8 (==1.0.6) ; extra == 'dev'
Requires-Dist: pytest-randomly (==3.4.1) ; extra == 'dev'
